{
    "items": [
        {
            "id": 1,
            "first_name": "Tonya",
            "last_name": "Belmont",
            "email": "tbelmont0@buzzfeed.com",
            "phone_number": "7045143539"
        },
        {
            "id": 2,
            "first_name": "Cletis",
            "last_name": "Huncoot",
            "email": "chuncoot1@auda.org.au",
            "phone_number": "4728931088"
        },
        {
            "id": 3,
            "first_name": "Andromache",
            "last_name": "Dockrill",
            "email": "adockrill2@barnesandnoble.com",
            "phone_number": "7629360763"
        },
        {
            "id": 4,
            "first_name": "Sephira",
            "last_name": "Daye",
            "email": "sdaye3@aol.com",
            "phone_number": "5013183295"
        },
        {
            "id": 5,
            "first_name": "Jobye",
            "last_name": "Yvens",
            "email": "jyvens4@google.co.uk",
            "phone_number": "1269707217"
        },
        {
            "id": 6,
            "first_name": "Brigid",
            "last_name": "Eates",
            "email": "beates5@princeton.edu",
            "phone_number": "9963893398"
        },
        {
            "id": 7,
            "first_name": "Lazarus",
            "last_name": "Shiell",
            "email": "lshiell6@ca.gov",
            "phone_number": "8799678232"
        },
        {
            "id": 8,
            "first_name": "Tawnya",
            "last_name": "Scolding",
            "email": "tscolding7@amazon.com",
            "phone_number": "6863341545"
        },
        {
            "id": 9,
            "first_name": "Raye",
            "last_name": "Langlands",
            "email": "rlanglands8@ebay.co.uk",
            "phone_number": "7109838841"
        },
        {
            "id": 10,
            "first_name": "Kissiah",
            "last_name": "Pietzker",
            "email": "kpietzker9@mayoclinic.com",
            "phone_number": "3127208472"
        },
        {
            "id": 11,
            "first_name": "Adeline",
            "last_name": "Prewer",
            "email": "aprewera@freewebs.com",
            "phone_number": "6064951224"
        },
        {
            "id": 12,
            "first_name": "Arabela",
            "last_name": "Faichney",
            "email": "afaichneyb@washingtonpost.com",
            "phone_number": "6542890721"
        },
        {
            "id": 13,
            "first_name": "Norbie",
            "last_name": "Stonham",
            "email": "nstonhamc@wunderground.com",
            "phone_number": "2541195941"
        },
        {
            "id": 14,
            "first_name": "Rudy",
            "last_name": "Lawless",
            "email": "rlawlessd@unicef.org",
            "phone_number": "6485648372"
        },
        {
            "id": 15,
            "first_name": "Bogart",
            "last_name": "Andrault",
            "email": "bandraulte@dmoz.org",
            "phone_number": "8258985100"
        },
        {
            "id": 16,
            "first_name": "Auroora",
            "last_name": "Taffrey",
            "email": "ataffreyf@phoca.cz",
            "phone_number": "3359886157"
        },
        {
            "id": 17,
            "first_name": "Karyn",
            "last_name": "Cross",
            "email": "kcrossg@gov.uk",
            "phone_number": "3151769687"
        }
    ]
}